{ "frames": [
   {
    "filename": "IdleDown0",
    "frame": { "x": 64, "y": 128, "w": 32, "h": 32 },
    "rotated": false,
    "trimmed": false,
    "spriteSourceSize": { "x": 0, "y": 0, "w": 32, "h": 32 },
    "sourceSize": { "w": 32, "h": 32 },
    "duration": 100
   },
   {
    "filename": "IdleDown1",
    "frame": { "x": 0, "y": 96, "w": 32, "h": 32 },
    "rotated": false,
    "trimmed": false,
    "spriteSourceSize": { "x": 0, "y": 0, "w": 32, "h": 32 },
    "sourceSize": { "w": 32, "h": 32 },
    "duration": 100
   },
   {
    "filename": "IdleDown2",
    "frame": { "x": 32, "y": 96, "w": 32, "h": 32 },
    "rotated": false,
    "trimmed": false,
    "spriteSourceSize": { "x": 0, "y": 0, "w": 32, "h": 32 },
    "sourceSize": { "w": 32, "h": 32 },
    "duration": 100
   },
   {
    "filename": "IdleDown3",
    "frame": { "x": 32, "y": 96, "w": 32, "h": 32 },
    "rotated": false,
    "trimmed": false,
    "spriteSourceSize": { "x": 0, "y": 0, "w": 32, "h": 32 },
    "sourceSize": { "w": 32, "h": 32 },
    "duration": 100
   },
   {
    "filename": "IdleDown4",
    "frame": { "x": 0, "y": 96, "w": 32, "h": 32 },
    "rotated": false,
    "trimmed": false,
    "spriteSourceSize": { "x": 0, "y": 0, "w": 32, "h": 32 },
    "sourceSize": { "w": 32, "h": 32 },
    "duration": 100
   },
   {
    "filename": "IdleDown5",
    "frame": { "x": 64, "y": 128, "w": 32, "h": 32 },
    "rotated": false,
    "trimmed": false,
    "spriteSourceSize": { "x": 0, "y": 0, "w": 32, "h": 32 },
    "sourceSize": { "w": 32, "h": 32 },
    "duration": 100
   },
   {
    "filename": "IdleRight0",
    "frame": { "x": 64, "y": 96, "w": 32, "h": 32 },
    "rotated": false,
    "trimmed": false,
    "spriteSourceSize": { "x": 0, "y": 0, "w": 32, "h": 32 },
    "sourceSize": { "w": 32, "h": 32 },
    "duration": 100
   },
   {
    "filename": "IdleRight1",
    "frame": { "x": 96, "y": 96, "w": 32, "h": 32 },
    "rotated": false,
    "trimmed": false,
    "spriteSourceSize": { "x": 0, "y": 0, "w": 32, "h": 32 },
    "sourceSize": { "w": 32, "h": 32 },
    "duration": 100
   },
   {
    "filename": "IdleRight2",
    "frame": { "x": 128, "y": 96, "w": 32, "h": 32 },
    "rotated": false,
    "trimmed": false,
    "spriteSourceSize": { "x": 0, "y": 0, "w": 32, "h": 32 },
    "sourceSize": { "w": 32, "h": 32 },
    "duration": 100
   },
   {
    "filename": "IdleRight3",
    "frame": { "x": 128, "y": 96, "w": 32, "h": 32 },
    "rotated": false,
    "trimmed": false,
    "spriteSourceSize": { "x": 0, "y": 0, "w": 32, "h": 32 },
    "sourceSize": { "w": 32, "h": 32 },
    "duration": 100
   },
   {
    "filename": "IdleRight4",
    "frame": { "x": 96, "y": 96, "w": 32, "h": 32 },
    "rotated": false,
    "trimmed": false,
    "spriteSourceSize": { "x": 0, "y": 0, "w": 32, "h": 32 },
    "sourceSize": { "w": 32, "h": 32 },
    "duration": 100
   },
   {
    "filename": "IdleRight5",
    "frame": { "x": 64, "y": 96, "w": 32, "h": 32 },
    "rotated": false,
    "trimmed": false,
    "spriteSourceSize": { "x": 0, "y": 0, "w": 32, "h": 32 },
    "sourceSize": { "w": 32, "h": 32 },
    "duration": 100
   },
   {
    "filename": "IdleUp0",
    "frame": { "x": 160, "y": 96, "w": 32, "h": 32 },
    "rotated": false,
    "trimmed": false,
    "spriteSourceSize": { "x": 0, "y": 0, "w": 32, "h": 32 },
    "sourceSize": { "w": 32, "h": 32 },
    "duration": 100
   },
   {
    "filename": "IdleUp1",
    "frame": { "x": 192, "y": 96, "w": 32, "h": 32 },
    "rotated": false,
    "trimmed": false,
    "spriteSourceSize": { "x": 0, "y": 0, "w": 32, "h": 32 },
    "sourceSize": { "w": 32, "h": 32 },
    "duration": 100
   },
   {
    "filename": "IdleUp2",
    "frame": { "x": 0, "y": 128, "w": 32, "h": 32 },
    "rotated": false,
    "trimmed": false,
    "spriteSourceSize": { "x": 0, "y": 0, "w": 32, "h": 32 },
    "sourceSize": { "w": 32, "h": 32 },
    "duration": 100
   },
   {
    "filename": "IdleUp3",
    "frame": { "x": 0, "y": 128, "w": 32, "h": 32 },
    "rotated": false,
    "trimmed": false,
    "spriteSourceSize": { "x": 0, "y": 0, "w": 32, "h": 32 },
    "sourceSize": { "w": 32, "h": 32 },
    "duration": 100
   },
   {
    "filename": "IdleUp4",
    "frame": { "x": 192, "y": 96, "w": 32, "h": 32 },
    "rotated": false,
    "trimmed": false,
    "spriteSourceSize": { "x": 0, "y": 0, "w": 32, "h": 32 },
    "sourceSize": { "w": 32, "h": 32 },
    "duration": 100
   },
   {
    "filename": "IdleUp5",
    "frame": { "x": 160, "y": 96, "w": 32, "h": 32 },
    "rotated": false,
    "trimmed": false,
    "spriteSourceSize": { "x": 0, "y": 0, "w": 32, "h": 32 },
    "sourceSize": { "w": 32, "h": 32 },
    "duration": 100
   },
   {
    "filename": "RunDown0",
    "frame": { "x": 32, "y": 128, "w": 32, "h": 32 },
    "rotated": false,
    "trimmed": false,
    "spriteSourceSize": { "x": 0, "y": 0, "w": 32, "h": 32 },
    "sourceSize": { "w": 32, "h": 32 },
    "duration": 100
   },
   {
    "filename": "RunDown1",
    "frame": { "x": 192, "y": 64, "w": 32, "h": 32 },
    "rotated": false,
    "trimmed": false,
    "spriteSourceSize": { "x": 0, "y": 0, "w": 32, "h": 32 },
    "sourceSize": { "w": 32, "h": 32 },
    "duration": 100
   },
   {
    "filename": "RunDown2",
    "frame": { "x": 96, "y": 128, "w": 32, "h": 32 },
    "rotated": false,
    "trimmed": false,
    "spriteSourceSize": { "x": 0, "y": 0, "w": 32, "h": 32 },
    "sourceSize": { "w": 32, "h": 32 },
    "duration": 100
   },
   {
    "filename": "RunDown3",
    "frame": { "x": 128, "y": 128, "w": 32, "h": 32 },
    "rotated": false,
    "trimmed": false,
    "spriteSourceSize": { "x": 0, "y": 0, "w": 32, "h": 32 },
    "sourceSize": { "w": 32, "h": 32 },
    "duration": 100
   },
   {
    "filename": "RunDown4",
    "frame": { "x": 160, "y": 128, "w": 32, "h": 32 },
    "rotated": false,
    "trimmed": false,
    "spriteSourceSize": { "x": 0, "y": 0, "w": 32, "h": 32 },
    "sourceSize": { "w": 32, "h": 32 },
    "duration": 100
   },
   {
    "filename": "RunDown5",
    "frame": { "x": 192, "y": 128, "w": 32, "h": 32 },
    "rotated": false,
    "trimmed": false,
    "spriteSourceSize": { "x": 0, "y": 0, "w": 32, "h": 32 },
    "sourceSize": { "w": 32, "h": 32 },
    "duration": 100
   },
   {
    "filename": "RunRight0",
    "frame": { "x": 0, "y": 160, "w": 32, "h": 32 },
    "rotated": false,
    "trimmed": false,
    "spriteSourceSize": { "x": 0, "y": 0, "w": 32, "h": 32 },
    "sourceSize": { "w": 32, "h": 32 },
    "duration": 100
   },
   {
    "filename": "RunRight1",
    "frame": { "x": 32, "y": 160, "w": 32, "h": 32 },
    "rotated": false,
    "trimmed": false,
    "spriteSourceSize": { "x": 0, "y": 0, "w": 32, "h": 32 },
    "sourceSize": { "w": 32, "h": 32 },
    "duration": 100
   },
   {
    "filename": "RunRight2",
    "frame": { "x": 64, "y": 160, "w": 32, "h": 32 },
    "rotated": false,
    "trimmed": false,
    "spriteSourceSize": { "x": 0, "y": 0, "w": 32, "h": 32 },
    "sourceSize": { "w": 32, "h": 32 },
    "duration": 100
   },
   {
    "filename": "RunRight3",
    "frame": { "x": 96, "y": 160, "w": 32, "h": 32 },
    "rotated": false,
    "trimmed": false,
    "spriteSourceSize": { "x": 0, "y": 0, "w": 32, "h": 32 },
    "sourceSize": { "w": 32, "h": 32 },
    "duration": 100
   },
   {
    "filename": "RunRight4",
    "frame": { "x": 96, "y": 32, "w": 32, "h": 32 },
    "rotated": false,
    "trimmed": false,
    "spriteSourceSize": { "x": 0, "y": 0, "w": 32, "h": 32 },
    "sourceSize": { "w": 32, "h": 32 },
    "duration": 100
   },
   {
    "filename": "RunRight5",
    "frame": { "x": 32, "y": 0, "w": 32, "h": 32 },
    "rotated": false,
    "trimmed": false,
    "spriteSourceSize": { "x": 0, "y": 0, "w": 32, "h": 32 },
    "sourceSize": { "w": 32, "h": 32 },
    "duration": 100
   },
   {
    "filename": "RunUp0",
    "frame": { "x": 64, "y": 0, "w": 32, "h": 32 },
    "rotated": false,
    "trimmed": false,
    "spriteSourceSize": { "x": 0, "y": 0, "w": 32, "h": 32 },
    "sourceSize": { "w": 32, "h": 32 },
    "duration": 100
   },
   {
    "filename": "RunUp1",
    "frame": { "x": 96, "y": 0, "w": 32, "h": 32 },
    "rotated": false,
    "trimmed": false,
    "spriteSourceSize": { "x": 0, "y": 0, "w": 32, "h": 32 },
    "sourceSize": { "w": 32, "h": 32 },
    "duration": 100
   },
   {
    "filename": "RunUp2",
    "frame": { "x": 128, "y": 0, "w": 32, "h": 32 },
    "rotated": false,
    "trimmed": false,
    "spriteSourceSize": { "x": 0, "y": 0, "w": 32, "h": 32 },
    "sourceSize": { "w": 32, "h": 32 },
    "duration": 100
   },
   {
    "filename": "RunUp3",
    "frame": { "x": 160, "y": 0, "w": 32, "h": 32 },
    "rotated": false,
    "trimmed": false,
    "spriteSourceSize": { "x": 0, "y": 0, "w": 32, "h": 32 },
    "sourceSize": { "w": 32, "h": 32 },
    "duration": 100
   },
   {
    "filename": "RunUp4",
    "frame": { "x": 192, "y": 0, "w": 32, "h": 32 },
    "rotated": false,
    "trimmed": false,
    "spriteSourceSize": { "x": 0, "y": 0, "w": 32, "h": 32 },
    "sourceSize": { "w": 32, "h": 32 },
    "duration": 100
   },
   {
    "filename": "RunUp5",
    "frame": { "x": 0, "y": 32, "w": 32, "h": 32 },
    "rotated": false,
    "trimmed": false,
    "spriteSourceSize": { "x": 0, "y": 0, "w": 32, "h": 32 },
    "sourceSize": { "w": 32, "h": 32 },
    "duration": 100
   },
   {
    "filename": "SlashDown0",
    "frame": { "x": 32, "y": 32, "w": 32, "h": 32 },
    "rotated": false,
    "trimmed": false,
    "spriteSourceSize": { "x": 0, "y": 0, "w": 32, "h": 32 },
    "sourceSize": { "w": 32, "h": 32 },
    "duration": 100
   },
   {
    "filename": "SlashDown1",
    "frame": { "x": 64, "y": 32, "w": 32, "h": 32 },
    "rotated": false,
    "trimmed": false,
    "spriteSourceSize": { "x": 0, "y": 0, "w": 32, "h": 32 },
    "sourceSize": { "w": 32, "h": 32 },
    "duration": 100
   },
   {
    "filename": "SlashDown2",
    "frame": { "x": 0, "y": 0, "w": 32, "h": 32 },
    "rotated": false,
    "trimmed": false,
    "spriteSourceSize": { "x": 0, "y": 0, "w": 32, "h": 32 },
    "sourceSize": { "w": 32, "h": 32 },
    "duration": 100
   },
   {
    "filename": "SlashDown3",
    "frame": { "x": 64, "y": 128, "w": 32, "h": 32 },
    "rotated": false,
    "trimmed": false,
    "spriteSourceSize": { "x": 0, "y": 0, "w": 32, "h": 32 },
    "sourceSize": { "w": 32, "h": 32 },
    "duration": 100
   },
   {
    "filename": "SlashRight0",
    "frame": { "x": 128, "y": 32, "w": 32, "h": 32 },
    "rotated": false,
    "trimmed": false,
    "spriteSourceSize": { "x": 0, "y": 0, "w": 32, "h": 32 },
    "sourceSize": { "w": 32, "h": 32 },
    "duration": 100
   },
   {
    "filename": "SlashRight1",
    "frame": { "x": 160, "y": 32, "w": 32, "h": 32 },
    "rotated": false,
    "trimmed": false,
    "spriteSourceSize": { "x": 0, "y": 0, "w": 32, "h": 32 },
    "sourceSize": { "w": 32, "h": 32 },
    "duration": 100
   },
   {
    "filename": "SlashRight2",
    "frame": { "x": 192, "y": 32, "w": 32, "h": 32 },
    "rotated": false,
    "trimmed": false,
    "spriteSourceSize": { "x": 0, "y": 0, "w": 32, "h": 32 },
    "sourceSize": { "w": 32, "h": 32 },
    "duration": 100
   },
   {
    "filename": "SlashRight3",
    "frame": { "x": 64, "y": 96, "w": 32, "h": 32 },
    "rotated": false,
    "trimmed": false,
    "spriteSourceSize": { "x": 0, "y": 0, "w": 32, "h": 32 },
    "sourceSize": { "w": 32, "h": 32 },
    "duration": 100
   },
   {
    "filename": "SlashUp0",
    "frame": { "x": 0, "y": 64, "w": 32, "h": 32 },
    "rotated": false,
    "trimmed": false,
    "spriteSourceSize": { "x": 0, "y": 0, "w": 32, "h": 32 },
    "sourceSize": { "w": 32, "h": 32 },
    "duration": 100
   },
   {
    "filename": "SlashUp1",
    "frame": { "x": 32, "y": 64, "w": 32, "h": 32 },
    "rotated": false,
    "trimmed": false,
    "spriteSourceSize": { "x": 0, "y": 0, "w": 32, "h": 32 },
    "sourceSize": { "w": 32, "h": 32 },
    "duration": 100
   },
   {
    "filename": "SlashUp2",
    "frame": { "x": 64, "y": 64, "w": 32, "h": 32 },
    "rotated": false,
    "trimmed": false,
    "spriteSourceSize": { "x": 0, "y": 0, "w": 32, "h": 32 },
    "sourceSize": { "w": 32, "h": 32 },
    "duration": 100
   },
   {
    "filename": "SlashUp3",
    "frame": { "x": 160, "y": 96, "w": 32, "h": 32 },
    "rotated": false,
    "trimmed": false,
    "spriteSourceSize": { "x": 0, "y": 0, "w": 32, "h": 32 },
    "sourceSize": { "w": 32, "h": 32 },
    "duration": 100
   },
   {
    "filename": "Die0",
    "frame": { "x": 64, "y": 96, "w": 32, "h": 32 },
    "rotated": false,
    "trimmed": false,
    "spriteSourceSize": { "x": 0, "y": 0, "w": 32, "h": 32 },
    "sourceSize": { "w": 32, "h": 32 },
    "duration": 100
   },
   {
    "filename": "Die1",
    "frame": { "x": 96, "y": 64, "w": 32, "h": 32 },
    "rotated": false,
    "trimmed": false,
    "spriteSourceSize": { "x": 0, "y": 0, "w": 32, "h": 32 },
    "sourceSize": { "w": 32, "h": 32 },
    "duration": 100
   },
   {
    "filename": "Die2",
    "frame": { "x": 128, "y": 64, "w": 32, "h": 32 },
    "rotated": false,
    "trimmed": false,
    "spriteSourceSize": { "x": 0, "y": 0, "w": 32, "h": 32 },
    "sourceSize": { "w": 32, "h": 32 },
    "duration": 100
   },
   {
    "filename": "Die3",
    "frame": { "x": 160, "y": 64, "w": 32, "h": 32 },
    "rotated": false,
    "trimmed": false,
    "spriteSourceSize": { "x": 0, "y": 0, "w": 32, "h": 32 },
    "sourceSize": { "w": 32, "h": 32 },
    "duration": 100
   }
 ],
 "meta": {
  "app": "http://www.aseprite.org/",
  "version": "1.3.13-dev",
  "image": "Player.png",
  "format": "RGBA8888",
  "size": { "w": 224, "h": 192 },
  "scale": "1",
  "frameTags": [
   { "name": "IdleDown", "from": 0, "to": 5, "direction": "forward", "color": "#000000ff" },
   { "name": "IdleRight", "from": 6, "to": 11, "direction": "forward", "color": "#000000ff" },
   { "name": "IdleUp", "from": 12, "to": 17, "direction": "forward", "color": "#000000ff" },
   { "name": "RunDown", "from": 18, "to": 23, "direction": "forward", "color": "#000000ff" },
   { "name": "RunRight", "from": 24, "to": 29, "direction": "forward", "color": "#000000ff" },
   { "name": "RunUp", "from": 30, "to": 35, "direction": "forward", "color": "#000000ff" },
   { "name": "SlashDown", "from": 36, "to": 39, "direction": "forward", "repeat": "1", "color": "#000000ff", "data": "next: IdleDown" },
   { "name": "SlashRight", "from": 40, "to": 43, "direction": "forward", "repeat": "1", "color": "#000000ff", "data": "next: IdleRight" },
   { "name": "SlashUp", "from": 44, "to": 47, "direction": "forward", "repeat": "1", "color": "#000000ff", "data": "next: IdleUp" },
   { "name": "Die", "from": 48, "to": 51, "direction": "forward", "repeat": "1", "color": "#000000ff" }
  ]
 }
}
